parcellate/__init__.py
parcellate/interfaces/__init__.py
parcellate/interfaces/qsirecon/__init__.py
parcellate/interfaces/qsirecon/loader.py
parcellate/interfaces/qsirecon/models.py
parcellate/interfaces/qsirecon/planner.py
parcellate/interfaces/qsirecon/qsirecon.py
parcellate/interfaces/qsirecon/runner.py
parcellate/metrics/__init__.py
parcellate/metrics/base.py
parcellate/metrics/volume.py
parcellate/parcellation/__init__.py
parcellate/parcellation/volume.py
parcellate/utils/__init__.py
parcellate/utils/image.py
parcellate-0.1.2.dist-info/METADATA
parcellate-0.1.2.dist-info/WHEEL
parcellate-0.1.2.dist-info/licenses/LICENSE
parcellate-0.1.2.dist-info/RECORD
