Metadata-Version: 2.4
Name: parcellate
Version: 0.1.2
Summary: A simple tool for extracting regional statistics from scalar neuroimaging maps.
Project-URL: Homepage, https://GalKepler.github.io/parcellate/
Project-URL: Repository, https://github.com/GalKepler/parcellate
Project-URL: Documentation, https://GalKepler.github.io/parcellate/
Author-email: Gal Kepler <galkepler@gmail.com>
License-File: LICENSE
Keywords: python
Classifier: Intended Audience :: Developers
Classifier: Programming Language :: Python
Classifier: Programming Language :: Python :: 3
Classifier: Programming Language :: Python :: 3.9
Classifier: Programming Language :: Python :: 3.10
Classifier: Programming Language :: Python :: 3.11
Classifier: Programming Language :: Python :: 3.12
Classifier: Programming Language :: Python :: 3.13
Classifier: Topic :: Software Development :: Libraries :: Python Modules
Requires-Python: <4.0,>=3.9
Requires-Dist: nibabel>=5.3.2
Requires-Dist: nilearn>=0.12.1
Requires-Dist: numpy>=2.0.2
Requires-Dist: pandas>=2.3.3
Requires-Dist: pybids>=0.20.0
Requires-Dist: seaborn>=0.13.2
Requires-Dist: tomli>=2.3.0
